selenol_platform/__init__.py
selenol_platform/cli.py
selenol_platform/config.py
selenol_platform/pool.py
selenol_platform-0.1.0.dist-info/DESCRIPTION.rst
selenol_platform-0.1.0.dist-info/METADATA
selenol_platform-0.1.0.dist-info/RECORD
selenol_platform-0.1.0.dist-info/WHEEL
selenol_platform-0.1.0.dist-info/entry_points.txt
selenol_platform-0.1.0.dist-info/metadata.json
selenol_platform-0.1.0.dist-info/top_level.txt
